be/__init__.py
be/startup.py
be/api/__init__.py
be/api/simple_node.py
fe/static/index.html
fe/static/nodes.html
fe/static/p2p-connection.js
app.json
avyas_aurica_base_apps_node_connection-3.0.9.dist-info/METADATA
avyas_aurica_base_apps_node_connection-3.0.9.dist-info/WHEEL
avyas_aurica_base_apps_node_connection-3.0.9.dist-info/RECORD
