Metadata-Version: 2.4
Name: avyas-aurica-base-apps-node-connection
Version: 3.0.9
Summary: Aurica app: node-connection
Requires-Python: >=3.11
Requires-Dist: fastapi>=0.104.0
Requires-Dist: uvicorn>=0.24.0
